tiktok_uploader/__init__.py
tiktok_uploader/__main__.py
tiktok_uploader/auth.py
tiktok_uploader/browsers.py
tiktok_uploader/cli.py
tiktok_uploader/config.py
tiktok_uploader/config.toml
tiktok_uploader/types.py
tiktok_uploader/upload.py
tiktok_uploader/utils.py
tiktok_uploader/proxy_auth_extension/__init__.py
tiktok_uploader/proxy_auth_extension/background.js
tiktok_uploader/proxy_auth_extension/manifest.json
tiktok_uploader/proxy_auth_extension/proxy_auth_extension.py
tiktok_uploader-1.1.5.dist-info/METADATA
tiktok_uploader-1.1.5.dist-info/WHEEL
tiktok_uploader-1.1.5.dist-info/entry_points.txt
tiktok_uploader-1.1.5.dist-info/licenses/LICENSE
tiktok_uploader-1.1.5.dist-info/RECORD
