Metadata-Version: 2.4
Name: tiktok-uploader
Version: 1.1.5
Summary: An automatic TikTok video uploader w/ CLI. Uploads videos automatically using an automated browser and your cookies for authentication.
Project-URL: Source Code, https://github.com/wkaisertexas/tiktok-uploader
Project-URL: Bug Tracker, https://github.com/wkaisertexas/tiktok-uploader/issues
Author-email: William Kaiser <wkaisertexas@gmail.com>
License-File: LICENSE
Keywords: Automation,CLI,Command Line,Python,Selenium,TikTok,Upload,Video
Classifier: License :: OSI Approved :: MIT License
Classifier: Operating System :: OS Independent
Classifier: Programming Language :: Python :: 3
Requires-Python: >=3.10
Requires-Dist: pydantic>=2.10.6
Requires-Dist: pytz>=2025.2
Requires-Dist: selenium>=3.141.0
Requires-Dist: toml>=0.10.2
Requires-Dist: webdriver-manager>=2.4.0
